m2dp/M2DP.py
m2dp/__init__.py
m2dp-0.1.2.data/scripts/M2DP.py
m2dp-0.1.2.data/scripts/__init__.py
m2dp-0.1.2.dist-info/METADATA
m2dp-0.1.2.dist-info/RECORD
m2dp-0.1.2.dist-info/WHEEL
m2dp-0.1.2.dist-info/top_level.txt
