Metadata-Version: 2.1
Name: m2dp
Version: 0.1.2
Summary: A python implementation of M2DP .
Home-page: https://github.com/adnan33/M2DP-python
Author: Adnan64
License: MIT
Platform: UNKNOWN
Classifier: Programming Language :: Python :: 3
Classifier: License :: OSI Approved :: MIT License
Classifier: Operating System :: OS Independent
